.DS_Store
RcTorch/__init__.py
RcTorch/clustering.py
RcTorch/custom_loss.py
RcTorch/defs.py
RcTorch/esn.py
RcTorch/esn_cv.py
RcTorch/esn_orig.py
RcTorch/hesn.py
RcTorch/old_backprop_code.py
RcTorch/scr.py
pyds2021/LinReg.py
pyds2021/__init__.py
pyds2021/plot.py
rctorch-private/__init__.py
rctorch-private/clustering.py
rctorch-private/custom_loss.py
rctorch-private/defs.py
rctorch-private/esn.py
rctorch-private/esn_cv.py
rctorch-private/esn_orig.py
rctorch-private/hesn.py
rctorch-private/old_backprop_code.py
rctorch-private/scr.py
rctorchprivate/__init__.py
rctorchprivate/clustering.py
rctorchprivate/custom_loss.py
rctorchprivate/defs.py
rctorchprivate/esn.py
rctorchprivate/esn_cv.py
rctorchprivate/esn_orig.py
rctorchprivate/hesn.py
rctorchprivate/old_backprop_code.py
rctorchprivate/scr.py
pyds2021-0.9.dist-info/AUTHORS
pyds2021-0.9.dist-info/LICENSE.txt
pyds2021-0.9.dist-info/METADATA
pyds2021-0.9.dist-info/WHEEL
pyds2021-0.9.dist-info/top_level.txt
pyds2021-0.9.dist-info/RECORD
